CHANGELOG.md
MANIFEST.in
README.rst
setup.cfg
setup.py
rattail_wave/__init__.py
rattail_wave/_version.py
rattail_wave/commands.py
rattail_wave/config.py
rattail_wave.egg-info/PKG-INFO
rattail_wave.egg-info/SOURCES.txt
rattail_wave.egg-info/dependency_links.txt
rattail_wave.egg-info/entry_points.txt
rattail_wave.egg-info/requires.txt
rattail_wave.egg-info/top_level.txt
rattail_wave/db/__init__.py
rattail_wave/db/alembic/versions/6a20ed366981_initial_wave_cache_tables.py
rattail_wave/db/model/__init__.py
rattail_wave/db/model/customers.py
rattail_wave/db/model/wave_cache.py
rattail_wave/importing/__init__.py
rattail_wave/importing/model.py
rattail_wave/importing/rattail.py
rattail_wave/importing/versions.py
rattail_wave/importing/wave.py